srcpy/__init__.py
srcpy/audio_to_bin_code.py
srcpy/bin_code_to_audio.py
srcpy/bin_code_to_time.py
srcpy/common.py
srcpy/time_to_bin_code.py
srcpy-0.1.7.data/scripts/play_wav.py
srcpy-0.1.7.data/scripts/src_to_time.py
srcpy-0.1.7.data/scripts/time_to_src.py
srcpy-0.1.7.dist-info/LICENSE
srcpy-0.1.7.dist-info/METADATA
srcpy-0.1.7.dist-info/WHEEL
srcpy-0.1.7.dist-info/top_level.txt
srcpy-0.1.7.dist-info/version.txt
srcpy-0.1.7.dist-info/version_full.txt
srcpy-0.1.7.dist-info/RECORD
